README.md
uea_ucr_datasets/__init__.py
uea_ucr_datasets/dataset.py
uea_ucr_datasets-0.1.2.dist-info/WHEEL
uea_ucr_datasets-0.1.2.dist-info/METADATA
uea_ucr_datasets-0.1.2.dist-info/RECORD
