Metadata-Version: 2.1
Name: uea-ucr-datasets
Version: 0.1.2
Summary: A small package for loading and handling UEA UCR time series classification datasets.
Home-page: https://github.com/BorgwardtLab/uea_ucr_datasets
Author: Max Horn
Author-email: max.horn@bsse.ethz.ch
Requires-Python: >=3.6,<4.0
Classifier: Programming Language :: Python :: 3
Classifier: Programming Language :: Python :: 3.6
Classifier: Programming Language :: Python :: 3.7
Requires-Dist: sktime (>=0.3,<0.4)
Project-URL: Repository, https://github.com/BorgwardtLab/uea_ucr_datasets
